{
    "copyright": "Copyright (c) 2017, 2022, Oracle Corporation and/or its affiliates.",
    "license": "Licensed under the Universal Permissive License v 1.0 as shown at https://oss.oracle.com/licenses/upl",
    "wlst_type": "Cluster${:s}",
    "online_bean": "weblogic.management.configuration.ClusterMBean",
    "child_folders_type": "multiple",
    "short_name": "Cluster",
    "folders": {
        "DynamicServers": {
            "wlst_type": "DynamicServers",
            "online_bean": "weblogic.management.configuration.DynamicServersMBean",
            "version": "[12.1.2,)",
            "default_name_value": "${NO_NAME_0:%CLUSTER%}",
            "folders": {},
            "attributes": {
                "CalculatedListenPorts":                [ {"version": "[12.1.2,)",   "wlst_mode": "both",    "wlst_name": "CalculatedListenPorts",                "wlst_path": "WP001", "default_value": "true",   "wlst_type": "boolean"          } ],
                "CalculatedMachineNames":               [ {"version": "[12.1.2,)",   "wlst_mode": "both",    "wlst_name": "CalculatedMachineNames",               "wlst_path": "WP001", "default_value": "false",  "wlst_type": "boolean"          } ],
                "DynamicClusterCooloffPeriodSeconds":   [ {"version": "[12.2.1,)",   "wlst_mode": "both",    "wlst_name": "DynamicClusterCooloffPeriodSeconds",   "wlst_path": "WP001", "default_value": 900,      "wlst_type": "integer"          } ],
                "DynamicClusterShutdownTimeoutSeconds": [ {"version": "[12.2.1,)",   "wlst_mode": "both",    "wlst_name": "DynamicClusterShutdownTimeoutSeconds", "wlst_path": "WP001", "default_value": 0,        "wlst_type": "integer"          } ],
                "DynamicClusterSize":                   [ {"version": "[12.2.1,)",   "wlst_mode": "both",    "wlst_name": "DynamicClusterSize",                   "wlst_path": "WP001", "default_value": 0,        "wlst_type": "integer"          } ],
                "DynamicServerName":                    [ {"version": "[12.2.1.3,)", "wlst_mode": "both",    "wlst_name": "DynamicServerName${:s}",               "wlst_path": "WP001", "default_value": null,     "wlst_type": "delimited_string", "access": "RO" } ],
                "IgnoreSessionsDuringShutdown":         [ {"version": "[12.2.1,)",   "wlst_mode": "both",    "wlst_name": "IgnoreSessionsDuringShutdown",         "wlst_path": "WP001", "default_value": "false",  "wlst_type": "boolean"          } ],
                "MachineMatchExpression":               [ {"version": "[12.2.1,)",   "wlst_mode": "both",    "wlst_name": "MachineMatchExpression",               "wlst_path": "WP001", "default_value": null,     "wlst_type": "string"           } ],
                "MachineMatchType":                     [ {"version": "[12.2.1,)",   "wlst_mode": "both",    "wlst_name": "MachineMatchType",                     "wlst_path": "WP001", "default_value": "${__NULL__:name}", "wlst_type": "string"     } ],
                "MachineNameMatchExpression":           [ {"version": "[12.1.2,)",   "wlst_mode": "both",    "wlst_name": "MachineNameMatchExpression",           "wlst_path": "WP001", "default_value": null,     "wlst_type": "string"           } ],
                "MaxDynamicClusterSize":                [ {"version": "[12.2.1,)",   "wlst_mode": "both",    "wlst_name": "MaxDynamicClusterSize",                "wlst_path": "WP001", "default_value": 8,        "wlst_type": "integer"          } ],
                "MaximumDynamicServerCount":            [ {"version": "[12.1.2,)",   "wlst_mode": "both",    "wlst_name": "MaximumDynamicServerCount",            "wlst_path": "WP001", "default_value": 0,        "wlst_type": "integer",         "get_method": "GET"  } ],
                "MinDynamicClusterSize":                [ {"version": "[12.2.1,)",   "wlst_mode": "both",    "wlst_name": "MinDynamicClusterSize",                "wlst_path": "WP001", "default_value": 1,        "wlst_type": "integer"          } ],
                "Notes":                                [ {"version": "[12.1.2,)",   "wlst_mode": "both",    "wlst_name": "Notes",                                "wlst_path": "WP001", "default_value": null,     "wlst_type": "string"           } ],
                "ServerNamePrefix":                     [ {"version": "[12.1.2,)",   "wlst_mode": "both",    "wlst_name": "ServerNamePrefix",                     "wlst_path": "WP001", "default_value": null,  "derived_default": "${:true}",   "wlst_type": "string"           } ],
                "ServerNameStartingIndex":              [ {"version": "[14.1.1,)",   "wlst_mode": "both",    "wlst_name": "ServerNameStartingIndex",              "wlst_path": "WP001", "default_value": 1,        "wlst_type": "integer"          } ],
                "ServerTemplate":                       [ {"version": "[12.1.2,)",   "wlst_mode": "both",    "wlst_name": "ServerTemplate",                       "wlst_path": "WP001", "default_value": null,     "wlst_type": "string",          "get_method": "${LSA:GET}", "set_method": "MBEAN.set_server_template_mbean", "set_mbean_type": "weblogic.management.configuration.ServerTemplateMBean" } ],
                "WaitForAllSessionsDuringShutdown":     [ {"version": "[12.2.1,)",   "wlst_mode": "both",    "wlst_name": "WaitForAllSessionsDuringShutdown",     "wlst_path": "WP001", "default_value": "false",  "wlst_type": "boolean"          } ]
            },
            "wlst_attributes_path": "WP001",
            "wlst_paths": {
                "WP001": "/Cluster${:s}/%CLUSTER%/DynamicServers/%DYNAMICSERVERS%"
            }
        },
        "CoherenceTier" : {
            "wlst_type": "CoherenceTier",
            "online_bean": "weblogic.management.configuration.CoherenceTierMBean",
            "version": "[12.1.2,)",
            "child_folders_type": "single",
            "default_name_value": "${NO_NAME_0:%CLUSTER%}",
            "folders" : {},
            "attributes" : {
                "CoherenceWebFederatedStorageEnabled": [ {"version": "[12.2.1.1,)", "wlst_mode": "both", "wlst_name": "CoherenceWebFederatedStorageEnabled", "wlst_path": "WP001", "default_value": "false",  "wlst_type": "boolean"  } ],
                "CoherenceWebLocalStorageEnabled":     [ {"version": "[12.1.2,)",   "wlst_mode": "both", "wlst_name": "CoherenceWebLocalStorageEnabled",     "wlst_path": "WP001", "default_value": "false",  "wlst_type": "boolean"  } ],
                "LocalStorageEnabled":                 [ {"version": "[12.1.2,)",   "wlst_mode": "both", "wlst_name": "LocalStorageEnabled",                 "wlst_path": "WP001", "default_value": "true",   "wlst_type": "boolean"  } ],
                "Notes":                               [ {"version": "[12.1.2,)",   "wlst_mode": "both", "wlst_name": "Notes",                               "wlst_path": "WP001", "default_value": null,     "wlst_type": "string"   } ]
            },
            "wlst_attributes_path": "WP001",
            "wlst_paths": {
                "WP001": "/Cluster${:s}/%CLUSTER%/CoherenceTier/%COHERENCETIER%"
            }
        },
        "DatabaseLessLeasingBasis" : {
            "wlst_type": "DatabaseLessLeasingBasis",
            "online_bean": "weblogic.management.configuration.DatabaseLessLeasingBasisMBean",
            "version": "[10.3.6,)",
            "default_name_value": "${NO_NAME_0:%CLUSTER%}",
            "folders": {},
            "attributes" : {
                "FenceTimeout":             [ {"version": "[10.3.6,)", "wlst_mode": "both",   "wlst_name": "FenceTimeout",                   "wlst_path": "WP001", "default_value": 5,        "wlst_type": "integer", "get_method": "${LSA:GET}" } ],
                "LeaderHeartbeatPeriod":    [ {"version": "[10.3.6,)", "wlst_mode": "both",   "wlst_name": "LeaderHeartbeatPeriod",          "wlst_path": "WP001", "default_value": 10,       "wlst_type": "integer", "get_method": "${LSA:GET}", "restart_required": "true" } ],
                "MemberDiscoveryTimeout":   [ {"version": "[10.3.6,)", "wlst_mode": "both",   "wlst_name": "MemberDiscoveryTimeout",         "wlst_path": "WP001", "default_value": 30,       "wlst_type": "integer", "restart_required": "true" } ],
                "MessageDeliveryTimeout":   [ {"version": "[10.3.6,)", "wlst_mode": "both",   "wlst_name": "MessageDeliveryTimeout",         "wlst_path": "WP001", "default_value": 5000,     "wlst_type": "integer", "get_method": "${LSA:GET}" } ],
                "NodeManagerTimeoutMillis": [ {"version": "[10.3.6,)", "wlst_mode": "both",   "wlst_name": "NodeManagerTimeoutMillis",       "wlst_path": "WP001", "default_value": 180000,   "wlst_type": "integer", "get_method": "${LSA:GET}" } ],
                "Notes":                    [ {"version": "[10.3.6,)", "wlst_mode": "both",   "wlst_name": "Notes",                          "wlst_path": "WP001", "default_value": null,     "wlst_type": "string"  } ],
                "PeriodicSrmCheckEnabled":  [ {"version": "[10.3.6,)", "wlst_mode": "both",   "wlst_name": "Periodic${Srm:SRM}CheckEnabled", "wlst_path": "WP001", "default_value": "true",   "wlst_type": "boolean", "get_method": "${LSA:GET}", "restart_required": "true" } ]
            },
            "wlst_attributes_path": "WP001",
            "wlst_paths": {
                "WP001": "/Cluster${:s}/%CLUSTER%/${(DatabaseLessLeasingBasis):DatabaseLessLeasingBasis}/%DATABASELESSLEASINGBASIS%"
            }
        },
        "JTACluster" : {
            "wlst_type": "JTACluster",
            "online_bean": "weblogic.management.configuration.JTAClusterMBean",
            "version": "[12.1.3,)",
            "child_folders_type": "single",
            "default_name_value": "${NO_NAME_0:%CLUSTER%}",
            "folders" : {},
            "attributes" : {
                "AbandonTimeoutSeconds":                      [ {"version": "[12.1.3,)",   "wlst_mode": "both",    "wlst_name": "AbandonTimeoutSeconds",                      "derived_default": "${:true}", "wlst_path": "WP001", "default_value": 86400,    "wlst_type": "integer" } ],
                "BeforeCompletionIterationLimit":             [ {"version": "[12.1.3,)",   "wlst_mode": "both",    "wlst_name": "BeforeCompletionIterationLimit",             "derived_default": "${:true}", "wlst_path": "WP001", "default_value": 10,       "wlst_type": "integer" } ],
                "CheckpointIntervalSeconds":                  [ {"version": "[12.1.3,)",   "wlst_mode": "both",    "wlst_name": "CheckpointIntervalSeconds",                  "derived_default": "${:true}", "wlst_path": "WP001", "default_value": 300,      "wlst_type": "integer" } ],
                "ClusterwideRecoveryEnabled":                 [ {"version": "[12.1.3,)",   "wlst_mode": "both",    "wlst_name": "ClusterwideRecoveryEnabled",                 "derived_default": "${:true}", "wlst_path": "WP001", "default_value": "false",  "wlst_type": "boolean" } ],
                "CompletionTimeoutSeconds":                   [ {"version": "[12.1.3,)",   "wlst_mode": "both",    "wlst_name": "CompletionTimeoutSeconds",                   "derived_default": "${:true}", "wlst_path": "WP001", "default_value": 0,        "wlst_type": "integer" } ],
                "CrossDomainRecoveryRetryInterval":           [ {"version": "[12.2.1,)",   "wlst_mode": "both",    "wlst_name": "CrossDomainRecoveryRetryInterval",           "derived_default": "${:true}", "wlst_path": "WP001", "default_value": 60,       "wlst_type": "integer" } ],
                "CrossSiteRecoveryLeaseExpiration":           [ {"version": "[12.2.1.1,)", "wlst_mode": "both",    "wlst_name": "CrossSiteRecoveryLeaseExpiration",           "derived_default": "${:true}", "wlst_path": "WP001", "default_value": 30,       "wlst_type": "integer" } ],
                "CrossSiteRecoveryLeaseUpdate":               [ {"version": "[12.2.1.1,)", "wlst_mode": "both",    "wlst_name": "CrossSiteRecoveryLeaseUpdate",               "derived_default": "${:true}", "wlst_path": "WP001", "default_value": 10,       "wlst_type": "integer" } ],
                "CrossSiteRecoveryRetryInterval":             [ {"version": "[12.2.1.1,)", "wlst_mode": "both",    "wlst_name": "CrossSiteRecoveryRetryInterval",             "derived_default": "${:true}", "wlst_path": "WP001", "default_value": 60,       "wlst_type": "integer" } ],
                "Determiner":                                 [ {"version": "[12.1.3,)",   "wlst_mode": "both",    "wlst_name": "Determiner${:s}",                            "wlst_path": "WP001", "default_value": null,     "wlst_type": "string"  } ],
                "DeterminerCandidateResourceInfoList":        [ {"version": "[12.2.1,)",   "wlst_mode": "online",  "wlst_name": "DeterminerCandidateResourceInfoList",      "wlst_path": "WP001", "default_value": "",       "wlst_type": "jarray",  "access": "RO" } ],
                "ForgetHeuristics":                           [ {"version": "[12.1.3,)",   "wlst_mode": "both",    "wlst_name": "ForgetHeuristics",                           "derived_default": "${:true}", "wlst_path": "WP001", "default_value": "true",   "wlst_type": "boolean" } ],
                "MaxResourceRequestsOnServer":                [ {"version": "[12.1.3,)",   "wlst_mode": "both",    "wlst_name": "MaxResourceRequestsOnServer",                "derived_default": "${:true}", "wlst_path": "WP001", "default_value": 50,       "wlst_type": "integer" } ],
                "MaxResourceUnavailableMillis":               [ {"version": "[12.1.3,)",   "wlst_mode": "both",    "wlst_name": "MaxResourceUnavailableMillis",               "derived_default": "${:true}", "wlst_path": "WP001", "default_value": 1800000,  "wlst_type": "long"    } ],
                "MaxRetrySecondsBeforeDeterminerFail":        [ {"version": "[12.2.1,)",   "wlst_mode": "both",    "wlst_name": "MaxRetrySecondsBeforeDeterminerFail",        "derived_default": "${:true}", "wlst_path": "WP001", "default_value": 300,      "wlst_type": "integer" } ],
                "MaxTransactions":                            [ {"version": "[12.1.3,)",   "wlst_mode": "both",    "wlst_name": "MaxTransactions",                            "derived_default": "${:true}", "wlst_path": "WP001", "default_value": 10000,    "wlst_type": "integer" } ],
                "MaxTransactionsHealthIntervalMillis":        [ {"version": "[12.1.3,)",   "wlst_mode": "both",    "wlst_name": "MaxTransactionsHealthIntervalMillis",        "derived_default": "${:true}", "wlst_path": "WP001", "default_value": 60000,    "wlst_type": "long"    } ],
                "MaxUniqueNameStatistics":                    [ {"version": "[12.1.3,)",   "wlst_mode": "both",    "wlst_name": "MaxUniqueNameStatistics",                    "derived_default": "${:true}", "wlst_path": "WP001", "default_value": 1000,     "wlst_type": "integer" } ],
                "MaxXACallMillis":                            [ {"version": "[12.1.3,)",   "wlst_mode": "both",    "wlst_name": "MaxXACallMillis",                            "derived_default": "${:true}", "wlst_path": "WP001", "default_value": 120000,   "wlst_type": "long"    } ],
                "MigrationCheckpointIntervalSeconds":         [ {"version": "[12.1.3,)",   "wlst_mode": "both",    "wlst_name": "MigrationCheckpointIntervalSeconds",         "derived_default": "${:true}", "wlst_path": "WP001", "default_value": 60,       "wlst_type": "integer" } ],
                "Notes":                                      [ {"version": "[12.1.3,)",   "wlst_mode": "both",    "wlst_name": "Notes",                                      "wlst_path": "WP001", "default_value": null,     "wlst_type": "string"  } ],
                "ParallelXADispatchPolicy":                   [ {"version": "[12.1.3,)",   "wlst_mode": "both",    "wlst_name": "ParallelXADispatchPolicy",                   "wlst_path": "WP001", "default_value": null,     "wlst_type": "string"  } ],
                "ParallelXAEnabled":                          [ {"version": "[12.1.3,)",   "wlst_mode": "both",    "wlst_name": "ParallelXAEnabled",                          "derived_default": "${:true}", "wlst_path": "WP001", "default_value": "true",   "wlst_type": "boolean" } ],
                "PurgeResourceFromCheckpointIntervalSeconds": [ {"version": "[12.1.3,)",   "wlst_mode": "both",    "wlst_name": "PurgeResourceFromCheckpointIntervalSeconds", "derived_default": "${:true}", "wlst_path": "WP001", "default_value": 86400,    "wlst_type": "integer" } ],
                "RecoverySiteName":                           [ {"version": "[12.2.1,)",   "wlst_mode": "both",    "wlst_name": "RecoverySiteName",                           "wlst_path": "WP001", "default_value": null,     "wlst_type": "string"  } ],
                "RecoveryThresholdMillis":                    [ {"version": "[12.1.3,)",   "wlst_mode": "both",    "wlst_name": "RecoveryThresholdMillis",                    "derived_default": "${:true}", "wlst_path": "WP001", "default_value": 300000,   "wlst_type": "long"    } ],
                "SecurityInteropMode":                        [ {"version": "[12.1.3,)",   "wlst_mode": "both",    "wlst_name": "SecurityInteropMode",                        "derived_default": "${:true}", "wlst_path": "WP001", "default_value": "${__NULL__:default}", "wlst_type": "string"  } ],
                "SerializeEnlistmentsGCIntervalMillis":       [ {"version": "[12.1.3,)",   "wlst_mode": "both",    "wlst_name": "SerializeEnlistmentsGCIntervalMillis",       "derived_default": "${:true}", "wlst_path": "WP001", "default_value": 30000,    "wlst_type": "long"    } ],
                "ShutdownGracePeriod":                        [ {"version": "[12.2.1,)",   "wlst_mode": "both",    "wlst_name": "ShutdownGracePeriod",                        "derived_default": "${:true}", "wlst_path": "WP001", "default_value": 180,      "wlst_type": "integer" } ],
                "TightlyCoupledTransactionsEnabled":          [ {"version": "[12.1.3,)",   "wlst_mode": "both",    "wlst_name": "TightlyCoupledTransactionsEnabled",          "derived_default": "${:true}", "wlst_path": "WP001", "default_value": "false",  "wlst_type": "boolean" } ],
                "TimeoutSeconds":                             [ {"version": "[12.1.3,)",   "wlst_mode": "both",    "wlst_name": "TimeoutSeconds",                             "derived_default": "${:true}", "wlst_path": "WP001", "default_value": 30,       "wlst_type": "integer" } ],
                "TlogWriteWhenDeterminerExistsEnabled":       [ {"version": "[12.1.3,)",   "wlst_mode": "both",    "wlst_name": "T${log:LOG}WriteWhenDeterminerExistsEnabled", "derived_default": "${:true}", "wlst_path": "WP001", "default_value": "false", "wlst_type": "boolean" } ],
                "TwoPhaseEnabled":                            [ {"version": "[12.1.3,)",   "wlst_mode": "both",    "wlst_name": "TwoPhaseEnabled",                            "derived_default": "${:true}", "wlst_path": "WP001", "default_value": "true",   "wlst_type": "boolean" } ],
                "UnregisterResourceGracePeriod":              [ {"version": "[12.1.3,)",   "wlst_mode": "both",    "wlst_name": "UnregisterResourceGracePeriod",              "derived_default": "${:true}", "wlst_path": "WP001", "default_value": 30,       "wlst_type": "integer" } ],
                "UseNonSecureAddressesForDomain":             [ {"version": "[12.2.1.4,)", "wlst_mode": "both",    "wlst_name": "UseNonSecureAddressesForDomain${:s}",        "wlst_path": "WP001", "default_value": null,     "wlst_type": "${delimited_string:jarray}", "get_method": "${LSA:GET}", "preferred_model_type": "delimited_string" } ],
                "UsePublicAddressesForRemoteDomain":          [ {"version": "[12.2.1.4,)", "wlst_mode": "both",    "wlst_name": "UsePublicAddressesForRemoteDomain${:s}",     "wlst_path": "WP001", "default_value": null,     "wlst_type": "${delimited_string:jarray}", "get_method": "${LSA:GET}", "preferred_model_type": "delimited_string" } ],
                "WsatIssuedTokenEnabled":                     [ {"version": "[12.1.3,)",   "wlst_mode": "both",    "wlst_name": "W${sat:SAT}IssuedTokenEnabled",              "wlst_path": "WP001", "default_value": "false",  "wlst_type": "boolean" } ],
                "WsatTransportSecurityMode":                  [ {"version": "[12.1.3,)",   "wlst_mode": "both",    "wlst_name": "W${sat:SAT}TransportSecurityMode",           "wlst_path": "WP001", "default_value": "${__NULL__:SSLNotRequired}",   "wlst_type": "string", "get_method": "LSA"  } ]
            },
            "wlst_attributes_path": "WP001",
            "wlst_paths": {
                "WP001": "/Cluster${:s}/%CLUSTER%/JTACluster/%JTACLUSTER%"
            }
        },
        "OverloadProtection" : {
            "wlst_type": "OverloadProtection",
            "online_bean": "weblogic.management.configuration.OverloadProtectionMBean",
            "child_folders_type": "single",
            "default_name_value": "${NO_NAME_0:%CLUSTER%}",
            "folders" : {
                "ServerFailureTrigger" : {
                    "wlst_type": "ServerFailureTrigger",
                    "online_bean": "weblogic.management.configuration.ServerFailureTriggerMBean",
                    "child_folders_type": "single",
                    "default_name_value": "${NO_NAME_0:%CLUSTER%}",
                    "folders" : {},
                    "attributes" : {
                        "MaxStuckThreadTime": [ {"version": "[10,)",           "wlst_mode": "both",   "wlst_name": "MaxStuckThreadTime", "wlst_path": "WP001", "default_value": 600,      "wlst_type": "integer" } ],
                        "StuckThreadCount":   [ {"version": "[10,)",           "wlst_mode": "both",   "wlst_name": "StuckThreadCount",   "wlst_path": "WP001", "default_value": 0,        "wlst_type": "integer", "get_method": "GET" } ],
                        "Notes":              [ {"version": "[10,)",           "wlst_mode": "both",   "wlst_name": "Notes",              "wlst_path": "WP001", "default_value": null,     "wlst_type": "string"  } ]
                },
                "wlst_attributes_path": "WP001",
                "wlst_paths": {
                    "WP001": "/Cluster${:s}/%CLUSTER%/OverloadProtection/%OVERLOADPROTECTION%/ServerFailureTrigger/%SERVERFAILURETRIGGER%"
                }
              }
            },
            "attributes" : {
                "FailureAction":                  [ {"version": "[10,)", "wlst_mode": "both", "wlst_name": "FailureAction",                  "wlst_path": "WP001", "default_value": "${__NULL__:no-action}", "derived_default": "${:true}", "wlst_type": "string"  } ],
                "FreeMemoryPercentHighThreshold": [ {"version": "[10,)", "wlst_mode": "both", "wlst_name": "FreeMemoryPercentHighThreshold", "wlst_path": "WP001", "default_value": 0,                    "derived_default": "${:true}", "wlst_type": "integer" } ],
                "FreeMemoryPercentLowThreshold":  [ {"version": "[10,)", "wlst_mode": "both", "wlst_name": "FreeMemoryPercentLowThreshold",  "wlst_path": "WP001", "default_value": 0,                    "derived_default": "${:true}", "wlst_type": "integer" } ],
                "Notes":                          [ {"version": "[10,)", "wlst_mode": "both", "wlst_name": "Notes",                          "wlst_path": "WP001", "default_value": null,                 "wlst_type": "string"  } ],
                "PanicAction":                    [ {"version": "[10,12.2.1)", "wlst_mode": "both", "wlst_name": "PanicAction",              "wlst_path": "WP001", "default_value": "${__NULL__:no-action}",  "derived_default": "${:true}", "wlst_type": "string"  } ,
                                                    {"version": "[12.2.1,)", "wlst_mode": "both", "wlst_name": "PanicAction",                "wlst_path": "WP001", "default_value": "${__NULL__:system-exit}", "derived_default": "${:true}", "wlst_type": "string" } ],
                "SharedCapacityForWorkManagers":  [ {"version": "[10,)", "wlst_mode": "both", "wlst_name": "SharedCapacityForWorkManagers",  "wlst_path": "WP001", "default_value": 65536,                "derived_default": "${:true}", "wlst_type": "integer" } ]

            },
            "wlst_attributes_path": "WP001",
            "wlst_paths": {
                "WP001": "/Cluster${:s}/%CLUSTER%/OverloadProtection/%OVERLOADPROTECTION%"
            }
      }
    },
    "attributes": {
        "AdditionalAutoMigrationAttempts":           [ {"version": "[10,)",         "wlst_mode": "both",    "wlst_name": "AdditionalAutoMigrationAttempts",           "wlst_path": "WP001", "default_value": 3,                            "wlst_type": "integer",          "restart_required": "true" } ],
        "AsyncSessionQueueTimeout":                  [ {"version": "[10,)",         "wlst_mode": "both",    "wlst_name": "AsyncSessionQueueTimeout",                  "wlst_path": "WP001", "default_value": 30,                           "wlst_type": "integer"           } ],
        "AutoMigrationTableName":                    [ {"version": "[10,)",         "wlst_mode": "both",    "wlst_name": "AutoMigrationTableName",                    "wlst_path": "WP001", "default_value": "ACTIVE",                     "wlst_type": "string",           "restart_required": "true" } ],
        "AutoMigrationTableCreationDdlFile":         [ {"version": "[14.1.1,)",     "wlst_mode": "both",    "wlst_name": "AutoMigrationTableCreationD${dl:DL}File",   "wlst_path": "WP001", "default_value": null,                         "wlst_type": "string"            } ],
        "AutoMigrationTableCreationPolicy":          [ {"version": "[14.1.1,)",     "wlst_mode": "both",    "wlst_name": "AutoMigrationTableCreationPolicy",          "wlst_path": "WP001", "default_value": null,                         "wlst_type": "string"            } ],
        "CandidateMachinesForMigratableServer":      [ {"version": "[10,)",         "wlst_mode": "online",  "wlst_name": "CandidateMachinesForMigratableServers",     "wlst_path": "WP001", "default_value": "[]",                         "wlst_type": "jarray",           "get_method": "GET", "restart_required": true }  ,
                                                       {"version": "[10,)",         "wlst_mode": "offline", "wlst_name": "CandidateMachinesForMigratableServer",      "wlst_path": "WP001", "default_value": null,                         "wlst_type": "delimited_string", "get_method": "LSA", "restart_required": true } ],
        "ClientCertProxyEnabled":                    [ {"version": "[10,)",         "wlst_mode": "both",    "wlst_name": "ClientCertProxyEnabled",                    "wlst_path": "WP001", "default_value": "false",                      "wlst_type": "boolean",          "restart_required": "true" } ],
        "ClusterAddress":                            [ {"version": "[10,)",         "wlst_mode": "both",    "wlst_name": "ClusterAddress",                            "wlst_path": "WP001", "default_value": null,                         "wlst_type": "string",           "restart_required": "true" } ],
        "ClusterBroadcastChannel":                   [ {"version": "[10,)",         "wlst_mode": "both",    "wlst_name": "ClusterBroadcastChannel",                   "wlst_path": "WP001", "default_value": null,                         "wlst_type": "string"            } ],
        "ClusterMessagingMode":                      [ {"version": "[10,12.1.1)",   "wlst_mode": "both",    "wlst_name": "ClusterMessagingMode",                      "wlst_path": "WP001", "default_value": "${unicast:multicast}",       "wlst_type": "string"            } ,
                                                       {"version": "[12.1.1,)",     "wlst_mode": "both",    "wlst_name": "ClusterMessagingMode",                      "wlst_path": "WP001", "default_value": "unicast",                    "wlst_type": "string"            } ],
        "ClusterType":                               [ {"version": "[10,)",         "wlst_mode": "both",    "wlst_name": "ClusterType",                               "wlst_path": "WP001", "default_value": null,                         "wlst_type": "string",           "restart_required": "true" } ],
        "CoherenceClusterSystemResource":            [ {"version": "[12.1.2,)",     "wlst_mode": "both",    "wlst_name": "CoherenceClusterSystemResource",            "wlst_path": "WP001", "default_value": null,                         "wlst_type": "string",           "get_method": "${LSA:GET}","set_method": "${:MBEAN.set_coherence_cluster_mbean}", "set_mbean_type": "${:weblogic.management.configuration.CoherenceClusterSystemResourceMBean}", "restart_required": "true" } ],
        "ConcurrentSingletonActivationEnabled":      [ {"version": "[12.2.1.3,)",   "wlst_mode": "both",    "wlst_name": "ConcurrentSingletonActivationEnabled",      "wlst_path": "WP001", "default_value": "false",                      "wlst_type": "boolean",          "restart_required": "true" } ],
        "ConsensusParticipants":                     [ {"version": "[10,)",         "wlst_mode": "both",    "wlst_name": "ConsensusParticipants",                     "wlst_path": "WP001", "default_value": 0,                            "wlst_type": "integer",          "get_method": "GET" } ],
        "DataSourceForAutomaticMigration":           [ {"version": "[10,)",         "wlst_mode": "both",    "wlst_name": "DataSourceForAutomaticMigration",           "wlst_path": "WP001", "default_value": null,                         "wlst_type": "string",           "get_method": "${LSA:GET}", "set_method": "MBEAN.set_data_source_mbean", "set_mbean_type": "weblogic.management.configuration.JDBCSystemResourceMBean", "restart_required": "true" } ],
        "DataSourceForJobScheduler":                 [ {"version": "[10,)",         "wlst_mode": "both",    "wlst_name": "DataSourceForJobScheduler",                 "wlst_path": "WP001", "default_value": null,                         "wlst_type": "string",           "set_method": "${:MBEAN.set_data_source_mbean}", "set_mbean_type": "${:weblogic.management.configuration.JDBCSystemResourceMBean}" } ],
        "DataSourceForSessionPersistence":           [ {"version": "[10,)",         "wlst_mode": "both",    "wlst_name": "DataSourceForSessionPersistence",           "wlst_path": "WP001", "default_value": null,                         "wlst_type": "string",           "set_method": "${:MBEAN.set_data_source_mbean}", "set_mbean_type": "${:weblogic.management.configuration.JDBCSystemResourceMBean}", "restart_required": "true" } ],
        "DatabaseLeasingBasisConnectionRetryCount":  [ {"version": "[12.1.3,)",     "wlst_mode": "both",    "wlst_name": "DatabaseLeasingBasisConnectionRetryCount",  "wlst_path": "WP001", "default_value": 1,                            "wlst_type": "integer",          "get_method": "GET", "restart_required": "true" } ],
        "DatabaseLeasingBasisConnectionRetryDelay":  [ {"version": "[12.1.3,)",     "wlst_mode": "both",    "wlst_name": "DatabaseLeasingBasisConnectionRetryDelay",  "wlst_path": "WP001", "default_value": 1000,                         "wlst_type": "long",             "restart_required": "true"} ],
        "DeathDetectorHeartbeatPeriod":              [ {"version": "[10,12.1.1)",   "wlst_mode": "online",  "wlst_name": "DeathDetectorHeartbeatPeriod",              "wlst_path": "WP001", "default_value": 1,                            "wlst_type": "integer",          "get_method": "${LSA:GET}", "restart_required": true },
                                                       {"version": "[12.1.1,)",     "wlst_mode": "both",    "wlst_name": "DeathDetectorHeartbeatPeriod",              "wlst_path": "WP001", "default_value": 1,                            "wlst_type": "integer",          "get_method": "${LSA:GET}", "restart_required": true } ],
        "DefaultLoadAlgorithm":                      [ {"version": "[10,)",         "wlst_mode": "both",    "wlst_name": "DefaultLoadAlgorithm",                      "wlst_path": "WP001", "default_value": "${__NULL__:round-robin}",    "wlst_type": "string"            } ],
        "FencingGracePeriodMillis":                  [ {"version": "[10,)",         "wlst_mode": "both",    "wlst_name": "FencingGracePeriodMillis",                  "wlst_path": "WP001", "default_value": 30000,                        "wlst_type": "integer",          "restart_required": "true" } ],
        "FrontendHTTPPort":                          [ {"version": "[10,)",         "wlst_mode": "both",    "wlst_name": "FrontendHTTPPort",                          "wlst_path": "WP001", "default_value": 0,                            "wlst_type": "integer",          "restart_required": "true" } ],
        "FrontendHTTPSPort":                         [ {"version": "[10,)",         "wlst_mode": "both",    "wlst_name": "FrontendHTTPSPort",                         "wlst_path": "WP001", "default_value": 0,                            "wlst_type": "integer",          "restart_required": "true" } ],
        "FrontendHost":                              [ {"version": "[10,)",         "wlst_mode": "both",    "wlst_name": "FrontendHost",                              "wlst_path": "WP001", "default_value": null,                         "wlst_type": "string",           "restart_required": "true" } ],
        "GreedySessionFlushInterval":                [ {"version": "[10,)",         "wlst_mode": "both",    "wlst_name": "GreedySessionFlushInterval",                "wlst_path": "WP001", "default_value": 3,                            "wlst_type": "integer"           } ],
        "HealthCheckIntervalMillis":                 [ {"version": "[10,)",         "wlst_mode": "both",    "wlst_name": "HealthCheckIntervalMillis",                 "wlst_path": "WP001", "default_value": 10000,                        "wlst_type": "integer",          "restart_required": "true" } ],
        "HealthCheckPeriodsUntilFencing":            [ {"version": "[10,14)",       "wlst_mode": "both",    "wlst_name": "HealthCheckPeriodsUntilFencing",            "wlst_path": "WP001", "default_value": 3,                            "wlst_type": "integer",          "restart_required": "true" }  ,
                                                       {"version": "[14,)",         "wlst_mode": "both",    "wlst_name": "HealthCheckPeriodsUntilFencing",            "wlst_path": "WP001", "default_value": 6,                            "wlst_type": "integer",          "restart_required": "true" } ],
        "HttpPingRetryCount":                        [
            {"version": "[10,12.2.1.3)",       "wlst_mode": "online",  "wlst_name": "HTTPPingRetryCount",          "wlst_path": "WP001", "default_value": 3, "wlst_type": "integer",  "get_method": "GET" },
            {"version": "[12.2.1.1,12.2.1.3)", "wlst_mode": "offline", "wlst_name": "HTTPPingRetryCount",          "wlst_path": "WP001", "default_value": 3, "wlst_type": "integer",  "get_method": "GET" },
            {"version": "[12.2.1.3,)",         "wlst_mode": "both",    "wlst_name": "${Http:HTTP}PingRetryCount",  "wlst_path": "WP001", "default_value": 3, "wlst_type": "integer",  "get_method": "GET" }
        ],
        "HttpTraceSupportEnabled":                   [ {"version": "[10,)",         "wlst_mode": "both",    "wlst_name": "HttpTraceSupportEnabled",                   "wlst_path": "WP001", "default_value": "false",                      "wlst_type": "boolean",          "restart_required": "true" } ],
        "IdlePeriodsUntilTimeout":                   [ {"version": "[10,)",         "wlst_mode": "both",    "wlst_name": "IdlePeriodsUntilTimeout",                   "wlst_path": "WP001", "default_value": 3,                            "wlst_type": "integer",          "restart_required": "true" } ],
        "InterClusterCommLinkHealthCheckInterval":   [ {"version": "[10,)",         "wlst_mode": "both",    "wlst_name": "InterClusterCommLinkHealthCheckInterval",   "wlst_path": "WP001", "default_value": 30000,                        "wlst_type": "integer"           } ],
        "JobSchedulerTableName":                     [ {"version": "[10,12.2.1)",   "wlst_mode": "both",    "wlst_name": "JobSchedulerTableName",                     "wlst_path": "WP001", "default_value": "weblogic_timers",            "wlst_type": "string",           "restart_required": "true" } ,
                                                       {"version": "[12.2.1,)",     "wlst_mode": "both",    "wlst_name": "JobSchedulerTableName",                     "wlst_path": "WP001", "default_value": "WEBLOGIC_TIMERS",            "wlst_type": "string",           "restart_required": "true" } ],
        "MaxSecondarySelectionAttempts":             [
            {"version": "[12.2.1.4.0.220105,12.2.1.4.0.220929)", "wlst_mode": "online",  "wlst_name": "MaxSecondarySelectionAttempts", "wlst_path": "WP001", "default_value": 0, "wlst_type": "integer"  },
            {"version": "[14.1.1.0.0.220105,14.1.1.0.0.221010)", "wlst_mode": "online",  "wlst_name": "MaxSecondarySelectionAttempts", "wlst_path": "WP001", "default_value": 0, "wlst_type": "integer"  },
            {"version": "[12.2.1.4.0.220929,14.1.1)",            "wlst_mode": "both",    "wlst_name": "MaxSecondarySelectionAttempts", "wlst_path": "WP001", "default_value": 0, "wlst_type": "integer"  },
            {"version": "[14.1.1.0.0.221010,)",                  "wlst_mode": "both",    "wlst_name": "MaxSecondarySelectionAttempts", "wlst_path": "WP001", "default_value": 0, "wlst_type": "integer"  }
        ],
        "MaxServerCountForHttpPing":                 [ {"version": "[10,)",         "wlst_mode": "both",    "wlst_name": "MaxServerCountForHttpPing",                 "wlst_path": "WP001", "default_value": 0,                            "wlst_type": "integer",          "get_method": "${LSA:GET}"    } ],
        "MemberDeathDetectorEnabled":                [ {"version": "[10,12.1.1)",   "wlst_mode": "online",  "wlst_name": "MemberDeathDetectorEnabled",                "wlst_path": "WP001", "default_value": "false",                      "wlst_type": "boolean",          "restart_required": "true" },
                                                       {"version": "[12.1.1,)",     "wlst_mode": "both",    "wlst_name": "MemberDeathDetectorEnabled",                "wlst_path": "WP001", "default_value": "false",                      "wlst_type": "boolean",          "restart_required": "true" } ],
        "MemberWarmupTimeoutSeconds":                [ {"version": "[10,12.1.2)",   "wlst_mode": "both",    "wlst_name": "MemberWarmupTimeoutSeconds",                "wlst_path": "WP001", "default_value": 30,                           "wlst_type": "integer",          "restart_required": "true" } ,
                                                       {"version": "[12.1.2,12.1.3)", "wlst_mode": "both",  "wlst_name": "MemberWarmupTimeoutSeconds",                "wlst_path": "WP001", "default_value": 0,                            "derived_default": "${:true}", "wlst_type": "integer",          "restart_required": "true" } ,
                                                       {"version": "[12.1.3,)",     "wlst_mode": "both",    "wlst_name": "MemberWarmupTimeoutSeconds",                "wlst_path": "WP001", "default_value": 0,                            "derived_default": "${:true}", "wlst_type": "integer"            } ],
        "MessageOrderingEnabled":                    [ {"version": "[10,12.1.1)",   "wlst_mode": "both",    "wlst_name": "MessageOrderingEnabled",                    "wlst_path": "WP001", "default_value": "false",                      "wlst_type": "boolean",          "restart_required": "true" } ,
                                                       {"version": "[12.1.1,12.1.2)", "wlst_mode": "both",  "wlst_name": "MessageOrderingEnabled",                    "wlst_path": "WP001", "default_value": "${false:true}",              "wlst_type": "boolean",          "restart_required": "true" } ,
                                                       {"version": "[12.1.2,)",     "wlst_mode": "both",    "wlst_name": "MessageOrderingEnabled",                    "wlst_path": "WP001", "default_value": "true",                       "wlst_type": "boolean",          "restart_required": "true" } ],
        "MigrationBasis":                            [ {"version": "[10,)",         "wlst_mode": "both",    "wlst_name": "MigrationBasis",                            "wlst_path": "WP001", "default_value": "${__NULL__:database}",       "wlst_type": "string",           "restart_required": "true" } ],
        "MillisToSleepBetweenAutoMigrationAttempts": [ {"version": "[10,)",         "wlst_mode": "both",    "wlst_name": "MillisToSleepBetweenAutoMigrationAttempts", "wlst_path": "WP001", "default_value": 180000,                       "wlst_type": "long",             "restart_required": "true" } ],
        "MulticastAddress":                          [ {"version": "[10,)",         "wlst_mode": "both",    "wlst_name": "MulticastAddress",                          "wlst_path": "WP001", "default_value": "239.192.0.0",                "wlst_type": "string",           "restart_required": "true" } ],
        "MulticastBufferSize":                       [ {"version": "[10,)",         "wlst_mode": "both",    "wlst_name": "MulticastBufferSize",                       "wlst_path": "WP001", "default_value": 64,                           "wlst_type": "integer",          "restart_required": "true" } ],
        "MulticastDataEncryption":                   [ {"version": "[10,)",         "wlst_mode": "both",    "wlst_name": "MulticastDataEncryption",                   "wlst_path": "WP001", "default_value": "false",                      "wlst_type": "boolean",          "restart_required": "true" } ],
        "MulticastPort":                             [ {"version": "[10,)",         "wlst_mode": "both",    "wlst_name": "MulticastPort",                             "wlst_path": "WP001", "default_value": 7001,                         "wlst_type": "integer",          "restart_required": "true" } ],
        "MulticastSendDelay":                        [ {"version": "[10,)",         "wlst_mode": "both",    "wlst_name": "MulticastSendDelay",                        "wlst_path": "WP001", "default_value": 3,                            "wlst_type": "integer",          "restart_required": "true" } ],
        "MulticastTTL":                              [ {"version": "[10,)",         "wlst_mode": "both",    "wlst_name": "MulticastTTL",                              "wlst_path": "WP001", "default_value": 1,                            "wlst_type": "integer",          "restart_required": "true" } ],
        "Notes":                                     [ {"version": "[10,)",         "wlst_mode": "both",    "wlst_name": "Notes",                                     "wlst_path": "WP001", "default_value": null,                         "wlst_type": "string"            } ],
        "NumberOfServersInClusterAddress":           [ {"version": "[10,)",         "wlst_mode": "both",    "wlst_name": "NumberOfServersInClusterAddress",           "wlst_path": "WP001", "default_value": 3,                            "wlst_type": "integer",          "restart_required": "true" } ],
        "OneWayRmiForReplicationEnabled":            [ {"version": "[10,)",         "wlst_mode": "both",    "wlst_name": "OneWayRmiForReplicationEnabled",            "wlst_path": "WP001", "default_value": "false",                      "wlst_type": "boolean",          "restart_required": "true" } ],
        "PersistSessionsOnShutdown":                 [ {"version": "[10,)",         "wlst_mode": "both",    "wlst_name": "PersistSessionsOnShutdown",                 "wlst_path": "WP001", "default_value": "false",                      "wlst_type": "boolean",          "restart_required": "true" } ],
        "ProxyServer":                               [ {"version": "[10,)",         "wlst_mode": "offline", "wlst_name": "ProxyServer",                               "wlst_path": "WP001", "default_value": null,                         "wlst_type": "string",           "restart_required": "true" } ],
        "RemoteClusterAddress":                      [ {"version": "[10,)",         "wlst_mode": "both",    "wlst_name": "RemoteClusterAddress",                      "wlst_path": "WP001", "default_value": null,                         "wlst_type": "string",           "restart_required": "true" } ],
        "ReplicationChannel":                        [ {"version": "[10,)",         "wlst_mode": "both",    "wlst_name": "ReplicationChannel",                        "wlst_path": "WP001", "default_value": "ReplicationChannel",         "wlst_type": "string",           "restart_required": "true" } ],
        "ReplicationTimeoutEnabled":                 [ {"version": "[10,)",         "wlst_mode": "both",    "wlst_name": "ReplicationTimeoutEnabled",                 "wlst_path": "WP001", "default_value": "true",                       "wlst_type": "boolean",          "restart_required": "true" } ],
        "SecureReplicationEnabled":                  [ {"version": "[10,)",         "wlst_mode": "both",    "wlst_name": "SecureReplicationEnabled",                  "wlst_path": "WP001", "default_value": "false",                      "wlst_type": "boolean"           } ],
        "ServiceActivationRequestResponseTimeout":   [ {"version": "[12.2.1,12.2.1.3)", "wlst_mode": "both", "wlst_name": "ServiceActivationRequestResponseTimeout",  "wlst_path": "WP001", "default_value": "10000",                      "wlst_type": "integer",          "restart_required": "true" },
                                                       {"version": "[12.2.1.3,)",   "wlst_mode": "both",    "wlst_name": "ServiceActivationRequestResponseTimeout",   "wlst_path": "WP001", "default_value": 0,                            "wlst_type": "integer",          "restart_required": "true" } ],
        "ServiceAgeThresholdSeconds":                [ {"version": "[10,)",         "wlst_mode": "both",    "wlst_name": "ServiceAgeThresholdSeconds",                "wlst_path": "WP001", "default_value": 180,                          "wlst_type": "integer"           } ],
        "SessionFlushInterval":                      [ {"version": "[10,)",         "wlst_mode": "both",    "wlst_name": "SessionFlushInterval",                      "wlst_path": "WP001", "default_value": 180,                          "wlst_type": "integer"           } ],
        "SessionFlushThreshold":                     [ {"version": "[10,)",         "wlst_mode": "both",    "wlst_name": "SessionFlushThreshold",                     "wlst_path": "WP001", "default_value": 10000,                        "wlst_type": "integer"           } ],
        "SessionLazyDeserializationEnabled":         [ {"version": "[10.3.4,12.2.1)", "wlst_mode": "both",  "wlst_name": "SessionLazyDeserializationEnabled",         "wlst_path": "WP001", "default_value": "false",                      "wlst_type": "boolean",          "restart_required": "true" },
                                                       {"version": "[12.2.1,)",     "wlst_mode": "both",    "wlst_name": "SessionLazyDeserializationEnabled",         "wlst_path": "WP001", "default_value": "false",                      "wlst_type": "boolean"           } ],
        "SessionStateQueryProtocolEnabled":          [ {"version": "[12.2.1,)",     "wlst_mode": "both",    "wlst_name": "SessionStateQueryProtocolEnabled",          "wlst_path": "WP001", "default_value": "false",                      "wlst_type": "boolean"           } ],
        "SessionStateQueryRequestTimeout":           [ {"version": "[12.2.1,)",     "wlst_mode": "both",    "wlst_name": "SessionStateQueryRequestTimeout",           "wlst_path": "WP001", "default_value": 30,                           "wlst_type": "integer"           } ],
        "SingletonSQLQueryHelper":                   [ {"version": "[10,12.1.2)",   "wlst_mode": "both",    "wlst_name": "SingletonS${ql:QL}QueryHelper",             "wlst_path": "WP001", "default_value": "",                           "wlst_type": "string",            "get_method": "${LSA:GET}", "restart_required": "true" },
                                                       {"version": "[12.1.2,)",     "wlst_mode": "both",    "wlst_name": "SingletonSQLQueryHelper",                   "wlst_path": "WP001", "default_value": "",                           "wlst_type": "string",            "get_method": "${LSA:GET}", "restart_required": "true" } ],
        "SingletonServiceRequestTimeout":            [ {"version": "[12.2.1.3,)",   "wlst_mode": "both",    "wlst_name": "SingletonServiceRequestTimeout",            "wlst_path": "WP001", "default_value": 30000,                        "wlst_type": "integer"           } ],
        "SiteName":                                  [ {"version": "[12.2.1.2,)",   "wlst_mode": "both",    "wlst_name": "SiteName",                                  "wlst_path": "WP001", "default_value": null,                         "wlst_type": "string"            } ],
        "TxnAffinityEnabled":                        [ {"version": "[12.1.3,)",     "wlst_mode": "both",    "wlst_name": "TxnAffinityEnabled",                        "wlst_path": "WP001", "default_value": "false",                      "wlst_type": "boolean",          "restart_required": "true" } ],
        "UnicastDiscoveryPeriodMillis":              [ {"version": "[10,)",         "wlst_mode": "both",    "wlst_name": "UnicastDiscoveryPeriodMillis",              "wlst_path": "WP001", "default_value": 3000,                         "wlst_type": "integer",          "get_method": "${LSA:GET}" } ],
        "UnicastReadTimeout":                        [ {"version": "[12.2.1.3,)",   "wlst_mode": "both",    "wlst_name": "UnicastReadTimeout",                        "wlst_path": "WP001", "default_value": 15000,                        "wlst_type": "integer"           } ],
        "WANSessionPersistenceTableName":            [ {"version": "[10,12.1.2)",   "wlst_mode": "offline", "wlst_name": "WanSessionPersistenceTableName",            "wlst_path": "WP001", "default_value": "WLS_WAN_PERSISTENCE_TABLE",  "wlst_type": "string",           "restart_required": "true" },
                                                       {"version": "[12.1.2,)",     "wlst_mode": "offline", "wlst_name": "WANSessionPersistenceTableName",            "wlst_path": "WP001", "default_value": "WLS_WAN_PERSISTENCE_TABLE",  "wlst_type": "string",           "restart_required": "true" },
                                                       {"version": "[10,)",         "wlst_mode": "online",  "wlst_name": "WANSessionPersistenceTableName",            "wlst_path": "WP001", "default_value": "WLS_WAN_PERSISTENCE_TABLE",  "wlst_type": "string",           "restart_required": "true" } ],
        "WeblogicPluginEnabled":                     [ {"version": "[10,)",         "wlst_mode": "both",    "wlst_name": "WeblogicPluginEnabled",                     "wlst_path": "WP001", "default_value": "false",                      "wlst_type": "boolean",          "restart_required": "true" } ]
    },
    "wlst_attributes_path": "WP001",
    "wlst_paths": {
        "WP001": "/Cluster${:s}/%CLUSTER%"
    }
}
